[
  {
    "wrapperType": "collection",
    "collectionType": "Album",
    "artistId": 387969348,
    "collectionId": 1440191219,
    "artistName": "Various Artists",
    "collectionName": "Peak Atmospherics V1",
    "collectionCensoredName": "Peak Atmospherics V1",
    "collectionViewUrl": "https://music.apple.com/us/album/peak-atmospherics-v1/1440191219?uo=4",
    "artworkUrl60": "https://is1-ssl.mzstatic.com/image/thumb/Music118/v4/eb/b2/81/ebb2819c-ca57-60f7-7523-7d5648a0e22d/00_Cover_Art.jpg/60x60bb.jpg",
    "artworkUrl100": "https://is1-ssl.mzstatic.com/image/thumb/Music118/v4/eb/b2/81/ebb2819c-ca57-60f7-7523-7d5648a0e22d/00_Cover_Art.jpg/100x100bb.jpg",
    "collectionPrice": 4.99,
    "collectionExplicitness": "notExplicit",
    "trackCount": 10,
    "copyright": "℗ 2019 Soundscapes Digital",
    "country": "USA",
    "currency": "USD",
    "releaseDate": "2019-01-28T08:00:00Z",
    "primaryGenreName": "Dance"
  },
  {
    "wrapperType": "track",
    "kind": "song",
    "artistId": 254718646,
    "collectionId": 1440191219,
    "trackId": 1440191220,
    "artistName": "Chris Sterio",
    "collectionName": "Peak Atmospherics V1",
    "trackName": "Peak Atmospherics V1",
    "collectionCensoredName": "Peak Atmospherics V1",
    "trackCensoredName": "Peak Atmospherics V1 (Atmospheric Journey)",
    "collectionArtistId": 387969348,
    "collectionArtistName": "Various Artists",
    "artistViewUrl": "https://music.apple.com/us/artist/chris-sterio/254718646?uo=4",
    "collectionViewUrl": "https://music.apple.com/us/album/peak-atmospherics-v1-atmospheric-journey/1440191219?i=1440191220&uo=4",
    "trackViewUrl": "https://music.apple.com/us/album/peak-atmospherics-v1-atmospheric-journey/1440191219?i=1440191220&uo=4",
    "previewUrl": "https://audio-ssl.itunes.apple.com/itunes-assets/AudioPreview122/v4/93/e7/6e/93e76e79-99a3-ff44-4cef-bb9d798184ba/mzaf_4488200431723786471.plus.aac.p.m4a",
    "artworkUrl30": "https://is1-ssl.mzstatic.com/image/thumb/Music118/v4/eb/b2/81/ebb2819c-ca57-60f7-7523-7d5648a0e22d/00_Cover_Art.jpg/30x30bb.jpg",
    "artworkUrl60": "https://is1-ssl.mzstatic.com/image/thumb/Music118/v4/eb/b2/81/ebb2819c-ca57-60f7-7523-7d5648a0e22d/00_Cover_Art.jpg/60x60bb.jpg",
    "artworkUrl100": "https://is1-ssl.mzstatic.com/image/thumb/Music118/v4/eb/b2/81/ebb2819c-ca57-60f7-7523-7d5648a0e22d/00_Cover_Art.jpg/100x100bb.jpg",
    "collectionPrice": 4.99,
    "trackPrice": -1.0,
    "releaseDate": "2019-01-28T12:00:00Z",
    "collectionExplicitness": "notExplicit",
    "trackExplicitness": "notExplicit",
    "discCount": 1,
    "discNumber": 1,
    "trackCount": 10,
    "trackNumber": 1,
    "trackTimeMillis": 3049805,
    "country": "USA",
    "currency": "USD",
    "primaryGenreName": "Dance",
    "isStreamable": true
  },
  {
    "wrapperType": "track",
    "kind": "song",
    "artistId": 916938698,
    "collectionId": 1440191219,
    "trackId": 1440191221,
    "artistName": "TasZ",
    "collectionName": "Peak Atmospherics V1",
    "trackName": "Dive",
    "collectionCensoredName": "Peak Atmospherics V1",
    "trackCensoredName": "Dive",
    "collectionArtistId": 387969348,
    "collectionArtistName": "Various Artists",
    "artistViewUrl": "https://music.apple.com/us/artist/tasz/916938698?uo=4",
    "collectionViewUrl": "https://music.apple.com/us/album/dive/1440191219?i=1440191221&uo=4",
    "trackViewUrl": "https://music.apple.com/us/album/dive/1440191219?i=1440191221&uo=4",
    "previewUrl": "https://audio-ssl.itunes.apple.com/itunes-assets/AudioPreview112/v4/9d/34/42/9d3442a2-8cc1-520c-25f4-93569b9a9270/mzaf_3123460220900566489.plus.aac.p.m4a",
    "artworkUrl30": "https://is1-ssl.mzstatic.com/image/thumb/Music118/v4/eb/b2/81/ebb2819c-ca57-60f7-7523-7d5648a0e22d/00_Cover_Art.jpg/30x30bb.jpg",
    "artworkUrl60": "https://is1-ssl.mzstatic.com/image/thumb/Music118/v4/eb/b2/81/ebb2819c-ca57-60f7-7523-7d5648a0e22d/00_Cover_Art.jpg/60x60bb.jpg",
    "artworkUrl100": "https://is1-ssl.mzstatic.com/image/thumb/Music118/v4/eb/b2/81/ebb2819c-ca57-60f7-7523-7d5648a0e22d/00_Cover_Art.jpg/100x100bb.jpg",
    "collectionPrice": 4.99,
    "trackPrice": 1.29,
    "releaseDate": "2017-06-26T12:00:00Z",
    "collectionExplicitness": "notExplicit",
    "trackExplicitness": "notExplicit",
    "discCount": 1,
    "discNumber": 1,
    "trackCount": 10,
    "trackNumber": 2,
    "trackTimeMillis": 520000,
    "country": "USA",
    "currency": "USD",
    "primaryGenreName": "Dance",
    "isStreamable": true
  },
  {
    "wrapperType": "track",
    "kind": "song",
    "artistId": 916938698,
    "collectionId": 1440191219,
    "trackId": 1440191222,
    "artistName": "TasZ",
    "collectionName": "Peak Atmospherics V1",
    "trackName": "Take the Time",
    "collectionCensoredName": "Peak Atmospherics V1",
    "trackCensoredName": "Take the Time",
    "collectionArtistId": 387969348,
    "collectionArtistName": "Various Artists",
    "artistViewUrl": "https://music.apple.com/us/artist/tasz/916938698?uo=4",
    "collectionViewUrl": "https://music.apple.com/us/album/take-the-time/1440191219?i=1440191222&uo=4",
    "trackViewUrl": "https://music.apple.com/us/album/take-the-time/1440191219?i=1440191222&uo=4",
    "previewUrl": "https://audio-ssl.itunes.apple.com/itunes-assets/AudioPreview112/v4/2c/30/8b/2c308bb6-82b1-2ca1-1648-21b646487a98/mzaf_15226352275595746240.plus.aac.p.m4a",
    "artworkUrl30": "https://is1-ssl.mzstatic.com/image/thumb/Music118/v4/eb/b2/81/ebb2819c-ca57-60f7-7523-7d5648a0e22d/00_Cover_Art.jpg/30x30bb.jpg",
    "artworkUrl60": "https://is1-ssl.mzstatic.com/image/thumb/Music118/v4/eb/b2/81/ebb2819c-ca57-60f7-7523-7d5648a0e22d/00_Cover_Art.jpg/60x60bb.jpg",
    "artworkUrl100": "https://is1-ssl.mzstatic.com/image/thumb/Music118/v4/eb/b2/81/ebb2819c-ca57-60f7-7523-7d5648a0e22d/00_Cover_Art.jpg/100x100bb.jpg",
    "collectionPrice": 4.99,
    "trackPrice": 1.29,
    "releaseDate": "2017-06-26T12:00:00Z",
    "collectionExplicitness": "notExplicit",
    "trackExplicitness": "notExplicit",
    "discCount": 1,
    "discNumber": 1,
    "trackCount": 10,
    "trackNumber": 3,
    "trackTimeMillis": 473000,
    "country": "USA",
    "currency": "USD",
    "primaryGenreName": "Dance",
    "isStreamable": true
  },
  {
    "wrapperType": "track",
    "kind": "song",
    "artistId": 1030220201,
    "collectionId": 1440191219,
    "trackId": 1440191223,
    "artistName": "Eric Rylos",
    "collectionName": "Peak Atmospherics V1",
    "trackName": "Daybreak",
    "collectionCensoredName": "Peak Atmospherics V1",
    "trackCensoredName": "Daybreak",
    "collectionArtistId": 387969348,
    "collectionArtistName": "Various Artists",
    "artistViewUrl": "https://music.apple.com/us/artist/eric-rylos/1030220201?uo=4",
    "collectionViewUrl": "https://music.apple.com/us/album/daybreak/1440191219?i=1440191223&uo=4",
    "trackViewUrl": "https://music.apple.com/us/album/daybreak/1440191219?i=1440191223&uo=4",
    "previewUrl": "https://audio-ssl.itunes.apple.com/itunes-assets/AudioPreview122/v4/00/8e/90/008e9002-31ee-6cce-6ade-2546281356d9/mzaf_4935139956606197696.plus.aac.p.m4a",
    "artworkUrl30": "https://is1-ssl.mzstatic.com/image/thumb/Music118/v4/eb/b2/81/ebb2819c-ca57-60f7-7523-7d5648a0e22d/00_Cover_Art.jpg/30x30bb.jpg",
    "artworkUrl60": "https://is1-ssl.mzstatic.com/image/thumb/Music118/v4/eb/b2/81/ebb2819c-ca57-60f7-7523-7d5648a0e22d/00_Cover_Art.jpg/60x60bb.jpg",
    "artworkUrl100": "https://is1-ssl.mzstatic.com/image/thumb/Music118/v4/eb/b2/81/ebb2819c-ca57-60f7-7523-7d5648a0e22d/00_Cover_Art.jpg/100x100bb.jpg",
    "collectionPrice": 4.99,
    "trackPrice": 1.29,
    "releaseDate": "2016-07-11T12:00:00Z",
    "collectionExplicitness": "notExplicit",
    "trackExplicitness": "notExplicit",
    "discCount": 1,
    "discNumber": 1,
    "trackCount": 10,
    "trackNumber": 4,
    "trackTimeMillis": 444000,
    "country": "USA",
    "currency": "USD",
    "primaryGenreName": "Dance",
    "isStreamable": true
  },
  {
    "wrapperType": "track",
    "kind": "song",
    "artistId": 1030220201,
    "collectionId": 1440191219,
    "trackId": 1440191224,
    "artistName": "Eric Rylos",
    "collectionName": "Peak Atmospherics V1",
    "trackName": "Dark Sky",
    "collectionCensoredName": "Peak Atmospherics V1",
    "trackCensoredName": "Dark Sky",
    "collectionArtistId": 387969348,
    "collectionArtistName": "Various Artists",
    "artistViewUrl": "https://music.apple.com/us/artist/eric-rylos/1030220201?uo=4",
    "collectionViewUrl": "https://music.apple.com/us/album/dark-sky/1440191219?i=1440191224&uo=4",
    "trackViewUrl": "https://music.apple.com/us/album/dark-sky/1440191219?i=1440191224&uo=4",
    "previewUrl": "https://audio-ssl.itunes.apple.com/itunes-assets/AudioPreview122/v4/6c/ee/57/6cee5734-c39a-e9ad-45f8-63c171a7ae18/mzaf_14348414151037191030.plus.aac.p.m4a",
    "artworkUrl30": "https://is1-ssl.mzstatic.com/image/thumb/Music118/v4/eb/b2/81/ebb2819c-ca57-60f7-7523-7d5648a0e22d/00_Cover_Art.jpg/30x30bb.jpg",
    "artworkUrl60": "https://is1-ssl.mzstatic.com/image/thumb/Music118/v4/eb/b2/81/ebb2819c-ca57-60f7-7523-7d5648a0e22d/00_Cover_Art.jpg/60x60bb.jpg",
    "artworkUrl100": "https://is1-ssl.mzstatic.com/image/thumb/Music118/v4/eb/b2/81/ebb2819c-ca57-60f7-7523-7d5648a0e22d/00_Cover_Art.jpg/100x100bb.jpg",
    "collectionPrice": 4.99,
    "trackPrice": 1.29,
    "releaseDate": "2016-07-11T12:00:00Z",
    "collectionExplicitness": "notExplicit",
    "trackExplicitness": "notExplicit",
    "discCount": 1,
    "discNumber": 1,
    "trackCount": 10,
    "trackNumber": 5,
    "trackTimeMillis": 226667,
    "country": "USA",
    "currency": "USD",
    "primaryGenreName": "Dance",
    "isStreamable": true
  },
  {
    "wrapperType": "track",
    "kind": "song",
    "artistId": 1076475148,
    "collectionId": 1440191219,
    "trackId": 1440191225,
    "artistName": "Abstrakted",
    "collectionName": "Peak Atmospherics V1",
    "trackName": "Magnetic Midnight",
    "collectionCensoredName": "Peak Atmospherics V1",
    "trackCensoredName": "Magnetic Midnight",
    "collectionArtistId": 387969348,
    "collectionArtistName": "Various Artists",
    "artistViewUrl": "https://music.apple.com/us/artist/abstrakted/1076475148?uo=4",
    "collectionViewUrl": "https://music.apple.com/us/album/magnetic-midnight/1440191219?i=1440191225&uo=4",
    "trackViewUrl": "https://music.apple.com/us/album/magnetic-midnight/1440191219?i=1440191225&uo=4",
    "previewUrl": "https://audio-ssl.itunes.apple.com/itunes-assets/AudioPreview122/v4/49/dc/11/49dc115c-2faf-0d48-80ef-3e9cf3051688/mzaf_16879745436275215637.plus.aac.p.m4a",
    "artworkUrl30": "https://is1-ssl.mzstatic.com/image/thumb/Music118/v4/eb/b2/81/ebb2819c-ca57-60f7-7523-7d5648a0e22d/00_Cover_Art.jpg/30x30bb.jpg",
    "artworkUrl60": "https://is1-ssl.mzstatic.com/image/thumb/Music118/v4/eb/b2/81/ebb2819c-ca57-60f7-7523-7d5648a0e22d/00_Cover_Art.jpg/60x60bb.jpg",
    "artworkUrl100": "https://is1-ssl.mzstatic.com/image/thumb/Music118/v4/eb/b2/81/ebb2819c-ca57-60f7-7523-7d5648a0e22d/00_Cover_Art.jpg/100x100bb.jpg",
    "collectionPrice": 4.99,
    "trackPrice": 1.29,
    "releaseDate": "2018-02-26T12:00:00Z",
    "collectionExplicitness": "notExplicit",
    "trackExplicitness": "notExplicit",
    "discCount": 1,
    "discNumber": 1,
    "trackCount": 10,
    "trackNumber": 6,
    "trackTimeMillis": 274844,
    "country": "USA",
    "currency": "USD",
    "primaryGenreName": "Dance",
    "isStreamable": true
  },
  {
    "wrapperType": "track",
    "kind": "song",
    "artistId": 1076475148,
    "collectionId": 1440191219,
    "trackId": 1440191226,
    "artistName": "Abstrakted",
    "collectionName": "Peak Atmospherics V1",
    "trackName": "Earth",
    "collectionCensoredName": "Peak Atmospherics V1",
    "trackCensoredName": "Earth",
    "collectionArtistId": 387969348,
    "collectionArtistName": "Various Artists",
    "artistViewUrl": "https://music.apple.com/us/artist/abstrakted/1076475148?uo=4",
    "collectionViewUrl": "https://music.apple.com/us/album/earth/1440191219?i=1440191226&uo=4",
    "trackViewUrl": "https://music.apple.com/us/album/earth/1440191219?i=1440191226&uo=4",
    "previewUrl": "https://audio-ssl.itunes.apple.com/itunes-assets/AudioPreview122/v4/c8/09/81/c80981af-9f6d-80d5-dc5e-2e5daf39a697/mzaf_2141074543362900357.plus.aac.p.m4a",
    "artworkUrl30": "https://is1-ssl.mzstatic.com/image/thumb/Music118/v4/eb/b2/81/ebb2819c-ca57-60f7-7523-7d5648a0e22d/00_Cover_Art.jpg/30x30bb.jpg",
    "artworkUrl60": "https://is1-ssl.mzstatic.com/image/thumb/Music118/v4/eb/b2/81/ebb2819c-ca57-60f7-7523-7d5648a0e22d/00_Cover_Art.jpg/60x60bb.jpg",
    "artworkUrl100": "https://is1-ssl.mzstatic.com/image/thumb/Music118/v4/eb/b2/81/ebb2819c-ca57-60f7-7523-7d5648a0e22d/00_Cover_Art.jpg/100x100bb.jpg",
    "collectionPrice": 4.99,
    "trackPrice": 1.29,
    "releaseDate": "2016-02-15T12:00:00Z",
    "collectionExplicitness": "notExplicit",
    "trackExplicitness": "notExplicit",
    "discCount": 1,
    "discNumber": 1,
    "trackCount": 10,
    "trackNumber": 7,
    "trackTimeMillis": 434816,
    "country": "USA",
    "currency": "USD",
    "primaryGenreName": "Dance",
    "isStreamable": true
  },
  {
    "wrapperType": "track",
    "kind": "song",
    "artistId": 1030220201,
    "collectionId": 1440191219,
    "trackId": 1440191227,
    "artistName": "Eric Rylos",
    "collectionName": "Peak Atmospherics V1",
    "trackName": "Fragments",
    "collectionCensoredName": "Peak Atmospherics V1",
    "trackCensoredName": "Fragments",
    "collectionArtistId": 387969348,
    "collectionArtistName": "Various Artists",
    "artistViewUrl": "https://music.apple.com/us/artist/eric-rylos/1030220201?uo=4",
    "collectionViewUrl": "https://music.apple.com/us/album/fragments/1440191219?i=1440191227&uo=4",
    "trackViewUrl": "https://music.apple.com/us/album/fragments/1440191219?i=1440191227&uo=4",
    "previewUrl": "https://audio-ssl.itunes.apple.com/itunes-assets/AudioPreview122/v4/fd/29/8c/fd298c24-1995-ef31-11a9-76fdac9170c7/mzaf_12205585337933977797.plus.aac.p.m4a",
    "artworkUrl30": "https://is1-ssl.mzstatic.com/image/thumb/Music118/v4/eb/b2/81/ebb2819c-ca57-60f7-7523-7d5648a0e22d/00_Cover_Art.jpg/30x30bb.jpg",
    "artworkUrl60": "https://is1-ssl.mzstatic.com/image/thumb/Music118/v4/eb/b2/81/ebb2819c-ca57-60f7-7523-7d5648a0e22d/00_Cover_Art.jpg/60x60bb.jpg",
    "artworkUrl100": "https://is1-ssl.mzstatic.com/image/thumb/Music118/v4/eb/b2/81/ebb2819c-ca57-60f7-7523-7d5648a0e22d/00_Cover_Art.jpg/100x100bb.jpg",
    "collectionPrice": 4.99,
    "trackPrice": 1.29,
    "releaseDate": "2017-12-25T12:00:00Z",
    "collectionExplicitness": "notExplicit",
    "trackExplicitness": "notExplicit",
    "discCount": 1,
    "discNumber": 1,
    "trackCount": 10,
    "trackNumber": 8,
    "trackTimeMillis": 148585,
    "country": "USA",
    "currency": "USD",
    "primaryGenreName": "Dance",
    "isStreamable": true
  },
  {
    "wrapperType": "track",
    "kind": "song",
    "artistId": 916938698,
    "collectionId": 1440191219,
    "trackId": 1440191228,
    "artistName": "TasZ",
    "collectionName": "Peak Atmospherics V1",
    "trackName": "Time to Go",
    "collectionCensoredName": "Peak Atmospherics V1",
    "trackCensoredName": "Time to Go",
    "collectionArtistId": 387969348,
    "collectionArtistName": "Various Artists",
    "artistViewUrl": "https://music.apple.com/us/artist/tasz/916938698?uo=4",
    "collectionViewUrl": "https://music.apple.com/us/album/time-to-go/1440191219?i=1440191228&uo=4",
    "trackViewUrl": "https://music.apple.com/us/album/time-to-go/1440191219?i=1440191228&uo=4",
    "previewUrl": "https://audio-ssl.itunes.apple.com/itunes-assets/AudioPreview112/v4/83/be/42/83be4283-c8b4-6dd2-2b12-53b8a7b90a75/mzaf_2279040243802181992.plus.aac.p.m4a",
    "artworkUrl30": "https://is1-ssl.mzstatic.com/image/thumb/Music118/v4/eb/b2/81/ebb2819c-ca57-60f7-7523-7d5648a0e22d/00_Cover_Art.jpg/30x30bb.jpg",
    "artworkUrl60": "https://is1-ssl.mzstatic.com/image/thumb/Music118/v4/eb/b2/81/ebb2819c-ca57-60f7-7523-7d5648a0e22d/00_Cover_Art.jpg/60x60bb.jpg",
    "artworkUrl100": "https://is1-ssl.mzstatic.com/image/thumb/Music118/v4/eb/b2/81/ebb2819c-ca57-60f7-7523-7d5648a0e22d/00_Cover_Art.jpg/100x100bb.jpg",
    "collectionPrice": 4.99,
    "trackPrice": 1.29,
    "releaseDate": "2017-06-26T12:00:00Z",
    "collectionExplicitness": "notExplicit",
    "trackExplicitness": "notExplicit",
    "discCount": 1,
    "discNumber": 1,
    "trackCount": 10,
    "trackNumber": 9,
    "trackTimeMillis": 522000,
    "country": "USA",
    "currency": "USD",
    "primaryGenreName": "Dance",
    "isStreamable": true
  },
  {
    "wrapperType": "track",
    "kind": "song",
    "artistId": 560396996,
    "collectionId": 1440191219,
    "trackId": 1440191229,
    "artistName": "Wolftek",
    "collectionName": "Peak Atmospherics V1",
    "trackName": "Lost in Purgatory",
    "collectionCensoredName": "Peak Atmospherics V1",
    "trackCensoredName": "Lost in Purgatory",
    "collectionArtistId": 387969348,
    "collectionArtistName": "Various Artists",
    "artistViewUrl": "https://music.apple.com/us/artist/wolftek/560396996?uo=4",
    "collectionViewUrl": "https://music.apple.com/us/album/lost-in-purgatory/1440191219?i=1440191229&uo=4",
    "trackViewUrl": "https://music.apple.com/us/album/lost-in-purgatory/1440191219?i=1440191229&uo=4",
    "previewUrl": "https://audio-ssl.itunes.apple.com/itunes-assets/AudioPreview112/v4/83/4d/00/834d0002-343a-9577-baa0-6c6f90f38e6b/mzaf_9348134147813172099.plus.aac.p.m4a",
    "artworkUrl30": "https://is1-ssl.mzstatic.com/image/thumb/Music118/v4/eb/b2/81/ebb2819c-ca57-60f7-7523-7d5648a0e22d/00_Cover_Art.jpg/30x30bb.jpg",
    "artworkUrl60": "https://is1-ssl.mzstatic.com/image/thumb/Music118/v4/eb/b2/81/ebb2819c-ca57-60f7-7523-7d5648a0e22d/00_Cover_Art.jpg/60x60bb.jpg",
    "artworkUrl100": "https://is1-ssl.mzstatic.com/image/thumb/Music118/v4/eb/b2/81/ebb2819c-ca57-60f7-7523-7d5648a0e22d/00_Cover_Art.jpg/100x100bb.jpg",
    "collectionPrice": 4.99,
    "trackPrice": 1.29,
    "releaseDate": "2015-12-21T12:00:00Z",
    "collectionExplicitness": "notExplicit",
    "trackExplicitness": "notExplicit",
    "discCount": 1,
    "discNumber": 1,
    "trackCount": 10,
    "trackNumber": 10,
    "trackTimeMillis": 510374,
    "country": "USA",
    "currency": "USD",
    "primaryGenreName": "Dance",
    "isStreamable": true
  }
]